lingodb/__init__.py
lingodb-0.0.4.dist-info/METADATA
lingodb-0.0.4.dist-info/WHEEL
lingodb-0.0.4.dist-info/top_level.txt
lingodb-0.0.4.dist-info/RECORD
