Metadata-Version: 2.4
Name: lingodb
Version: 0.0.4
Requires-Dist: lingodb-bridge===0.0.4
